jupyterlab_discovery/__init__.py
jupyterlab_discovery/_version.py
jupyterlab_discovery/handlers.py
jupyterlab_discovery/server_extension.py
jupyterlab_discovery-5.1.2.data/data/etc/jupyter/jupyter_notebook_config.d/jupyterlab-discovery.json
jupyterlab_discovery-5.1.2.data/data/share/jupyter/lab/extensions/jupyterlab_discovery-5.1.2.tgz
jupyterlab_discovery-5.1.2.dist-info/METADATA
jupyterlab_discovery-5.1.2.dist-info/RECORD
jupyterlab_discovery-5.1.2.dist-info/WHEEL
jupyterlab_discovery-5.1.2.dist-info/entry_points.txt
jupyterlab_discovery-5.1.2.dist-info/top_level.txt
