Metadata-Version: 2.1
Name: jupyterlab-discovery
Version: 5.1.2
Summary: A JupyterLab extension to facilitate the discovery and installation of other extensions
Home-page: http://github.com/vidartf/jupyterlab_discovery
Author: Vidar Tonaas Fauske
Author-email: vidartf@gmail.com
License: BSD
Keywords: Interactive,Interpreter,Shell,Web
Platform: Linux
Platform: Mac OS X
Platform: Windows
Classifier: Intended Audience :: Developers
Classifier: Intended Audience :: System Administrators
Classifier: Intended Audience :: Science/Research
Classifier: License :: OSI Approved :: BSD License
Classifier: Programming Language :: Python
Classifier: Programming Language :: Python :: 2.7
Classifier: Programming Language :: Python :: 3
Classifier: Programming Language :: Python :: 3.3
Classifier: Programming Language :: Python :: 3.4
Classifier: Programming Language :: Python :: 3.5
Classifier: Framework :: Jupyter
Provides-Extra: test
Requires-Dist: jupyterlab
Requires-Dist: tornado
Requires-Dist: notebook
Provides-Extra: test
